{
  "schema": "voidly-pay-network-health/v1",
  "generated_at": "2026-06-29T01:22:46.190Z",
  "run_id": "28342825314",
  "run_url": null,
  "health": {
    "ok": true,
    "system_frozen": false,
    "latency_ms": 458,
    "counts": {
      "wallets": 6343,
      "transfers_settled_24h": 1744,
      "active_admin_keys": 2
    }
  },
  "stats_summary": {
    "wallets": 6343,
    "active_capabilities": 19,
    "distinct_providers": 7,
    "hires_total": 23329,
    "hires_completed": 17564,
    "value_settled_cr": 15.0396
  },
  "providers": [
    {
      "did": "did:voidly:3bzjV3jSMCuTwZ6NRzrS8m",
      "capability": "echo.text-1777170066728",
      "capability_id": "ea0ac3a8-b35c-44c2-bf76-4c964c8dd559",
      "price_micro": 100,
      "status": "hire_failed",
      "error": "hire c802d91e-feaf-4ce2-85bc-1dc27248c7f3 did not reach claimed state (got requested)",
      "latency_ms": 62548
    },
    {
      "did": "did:voidly:Ck56rQkhsBe3bJa62bg81t",
      "capability": "echo.text-1777170057372",
      "capability_id": "4f862bbb-050b-47a6-a189-71a23d10b936",
      "price_micro": 100,
      "status": "hire_failed",
      "error": "hire 92894288-6a73-4f71-a2a0-47625f3f93d3 did not reach claimed state (got requested)",
      "latency_ms": 62542
    },
    {
      "did": "did:voidly:AsAVzZ2dtMrntgGRco8KkW",
      "capability": "hash.sha256",
      "capability_id": "e00a3caf-5090-4414-aab9-89e5420bf871",
      "price_micro": 800,
      "status": "ok",
      "receipt_state": "pending_acceptance",
      "receipt_id": "11c16e2d-bc5e-430e-9376-10b28011d833",
      "accepted": true,
      "verified": true,
      "latency_ms": 7330
    },
    {
      "did": "did:voidly:Eg8JvTNrBLcpbX3r461jJB",
      "capability": "hash.sha256",
      "capability_id": "1b32805f-07e0-426e-a7a2-53ac41396303",
      "price_micro": 1000,
      "status": "ok",
      "receipt_state": "pending_acceptance",
      "receipt_id": "70e14d77-ac9a-4dbd-9fbf-07834f4d1b9f",
      "accepted": true,
      "verified": true,
      "latency_ms": 11385
    },
    {
      "did": "did:voidly:8dtaBupp8ZZoaB8CQHBp2U",
      "capability": "bb.test.cap",
      "capability_id": "492df64a-df3e-47fb-bc67-ec6008835880",
      "price_micro": 1000,
      "status": "hire_failed",
      "error": "hire aacd8f5f-a439-40c9-90c9-8077606c286b did not reach claimed state (got requested)",
      "latency_ms": 62568
    },
    {
      "did": "did:voidly:mkt-b-1776622972",
      "capability": "translate",
      "capability_id": "af7719a4-f4bf-4a8c-aafb-8c1a7b8e226c",
      "price_micro": 500000,
      "status": "hire_failed",
      "error": "hire 6ea7a30c-65d9-443e-89fc-568c90d63d03 did not reach claimed state (got requested)",
      "latency_ms": 62473
    }
  ],
  "ok": false,
  "summary": {
    "providers_probed": 6,
    "providers_ok": 2,
    "providers_failing": 4,
    "success_rate": 0.3333333333333333
  }
}