{
  "schema": "voidly-pay-network-health/v1",
  "generated_at": "2026-04-20T01:55:21.737Z",
  "run_id": "24644817630",
  "run_url": "https://github.com/voidly-ai/voidly-pay/actions/runs/24644817630",
  "health": {
    "ok": true,
    "system_frozen": false,
    "latency_ms": 604,
    "counts": {
      "wallets": 30,
      "transfers_settled_24h": 1,
      "active_admin_keys": 1
    }
  },
  "stats_summary": {
    "wallets": 30,
    "active_capabilities": 16,
    "distinct_providers": 3,
    "hires_total": 113,
    "hires_completed": 107,
    "value_settled_cr": 0.6938
  },
  "providers": [
    {
      "did": "did:voidly:AsAVzZ2dtMrntgGRco8KkW",
      "capability": "hash.sha256",
      "capability_id": "e00a3caf-5090-4414-aab9-89e5420bf871",
      "price_micro": 800,
      "status": "ok",
      "receipt_state": "pending_acceptance",
      "receipt_id": "0bf77109-de33-4809-872a-c85e3bbaf02f",
      "accepted": true,
      "verified": true,
      "latency_ms": 11154
    },
    {
      "did": "did:voidly:Eg8JvTNrBLcpbX3r461jJB",
      "capability": "hash.sha256",
      "capability_id": "1b32805f-07e0-426e-a7a2-53ac41396303",
      "price_micro": 1000,
      "status": "ok",
      "receipt_state": "pending_acceptance",
      "receipt_id": "3b67a1be-d294-4c30-b36e-d9e2a6935c9c",
      "accepted": true,
      "verified": true,
      "latency_ms": 9089
    },
    {
      "did": "did:voidly:mkt-b-1776622972",
      "capability": "translate",
      "capability_id": "af7719a4-f4bf-4a8c-aafb-8c1a7b8e226c",
      "price_micro": 500000,
      "status": "hire_failed",
      "error": "hire 61cb69c8-39b3-43d2-b9a5-85188c26959a did not reach claimed state (got requested)",
      "latency_ms": 61846
    }
  ],
  "ok": false,
  "summary": {
    "providers_probed": 3,
    "providers_ok": 2,
    "providers_failing": 1,
    "success_rate": 0.6666666666666666
  }
}